xaal/__init__.py
xaal/hq433/__init__.py
xaal/hq433/__main__.py
xaal/hq433/gw.py
xaal_hq433-0.1.2.dist-info/METADATA
xaal_hq433-0.1.2.dist-info/WHEEL
xaal_hq433-0.1.2.dist-info/top_level.txt
xaal_hq433-0.1.2.dist-info/RECORD
