Metadata-Version: 2.4
Name: xaal.hq433
Version: 0.1.2
Summary: xAAL devices for HQ Product RF433 power switch
Author-email: Jerome Kerdreux <Jerome.Kerdreux@imt-atlantique.fr>
License-Expression: GPL-3.0-or-later
Project-URL: Homepage, https://recherche.imt-atlantique.fr/xaal/
Project-URL: Documentation, https://gitlab.imt-atlantique.fr/xaal/code/python/-/blob/main/devices/protocols/HQ433/README.rst
Project-URL: Source, https://gitlab.imt-atlantique.fr/xaal/code/python/-/tree/main/devices/protocols/HQ433
Keywords: xaal,rf433
Classifier: Programming Language :: Python
Classifier: Topic :: Software Development :: Libraries :: Python Modules
Requires-Dist: xaal.lib
Requires-Dist: pyserial
